vfi/__init__.py
vfi/_version.py
vfi/_vfi.py
vfi/tests/__init__.py
vfi/tests/test_common.py
vfi-0.1.1.dist-info/LICENSE
vfi-0.1.1.dist-info/METADATA
vfi-0.1.1.dist-info/WHEEL
vfi-0.1.1.dist-info/top_level.txt
vfi-0.1.1.dist-info/RECORD
